simpsons_classifier/__init__.py
simpsons_classifier/api.py
simpsons_classifier/config.py
simpsons_classifier/deps.py
simpsons_classifier/main.py
simpsons_classifier/model.py
simpsons_classifier_sheregeda-0.2.0.dist-info/LICENSE
simpsons_classifier_sheregeda-0.2.0.dist-info/METADATA
simpsons_classifier_sheregeda-0.2.0.dist-info/WHEEL
simpsons_classifier_sheregeda-0.2.0.dist-info/top_level.txt
simpsons_classifier_sheregeda-0.2.0.dist-info/RECORD
